{"92Izoukt/VK+/VWTg0dKfQ==":"slide3-1024x576.jpg","qKkGXK5PuUMwHMUPgkazTQ==":"mbr-256x188.png","3aaA9GuFyjFuO4Q/wEPktA==":"logo2-512x220.png","FvQFb1CyC7tGAhU4ICHZyQ==":"r464-3-2000x2000.png","q6zv6vbvz8MQVKz6DcYNAQ==":"r464-6-2000x2000.png","YYkXH0xzrnLCKNdFH/MBnw==":"r464-7-2000x2000.png","1aF893R/EgY65cgLKONsiQ==":"cara's_official_logo%20(1)-96x96.png","wETniIhr54ZiHoNN4oTCOQ==":"brand-96x74.png","Gc8smAeancqOi8y11LZOuA==":"r464-1-1108x1108.png","f7+TvDnU611Iw4fR240TDw==":"r464-2-606x565.jpg","KTqHXQ1lCLbKs3T7d8eunA==":"r464-3-614x576.jpg","gBuWaOU2kB+9+ijPrnAaGg==":"r464-4-618x578.jpg","zgiRanA5W6qC3FEP5aLlrQ==":"r464-5-552x467.jpg","Er6DeMZ3isyc1w0Li6TlRw==":"r464-1-618x610.jpg","Hi6DkaOGXTGWd9nQFUP+wQ==":"r464-4-614x574.jpg"}